munch-stubs/__init__.pyi
munch_stubs-0.1.3.dist-info/LICENSE
munch_stubs-0.1.3.dist-info/METADATA
munch_stubs-0.1.3.dist-info/WHEEL
munch_stubs-0.1.3.dist-info/top_level.txt
munch_stubs-0.1.3.dist-info/RECORD
