Metadata-Version: 2.1
Name: munch-stubs
Version: 0.1.3
Summary: Mypy plugin and stubs for munch
Home-page: https://github.com/MartinThoma/munch-stubs
Author: Martin Thoma
Author-email: info@martin-thoma.de
Maintainer: Martin Thoma
Maintainer-email: info@martin-thoma.de
License: MIT license
Download-URL: https://github.com/MartinThoma/munch-stubs
Keywords: utility,mypy,stubs
Platform: UNKNOWN
Classifier: Development Status :: 4 - Beta
Classifier: Intended Audience :: Developers
Classifier: Natural Language :: English
License-File: LICENSE
Requires-Dist: mypy >=0.720
Requires-Dist: typing-extensions >=3.7.4
Requires-Dist: munch >=2.5.0
